{
  "gitSyncId": "66a1f20e37084f3e785766c6_79495a09-ef81-4a96-86a1-3817131ceaae",
  "id": "Client_JSObject1.Table1primaryColumnscustomColumn7onClick",
  "pluginId": "js-plugin",
  "pluginType": "JS",
  "unpublishedAction": {
    "actionConfiguration": {
      "encodeParamsToggle": true,
      "jsArguments": [],
      "paginationType": "NONE",
      "timeoutInMillisecond": 10000
    },
    "clientSideExecution": true,
    "collectionId": "Client_JSObject1",
    "confirmBeforeExecute": false,
    "datasource": {
      "isAutoGenerated": false,
      "name": "UNUSED_DATASOURCE",
      "pluginId": "js-plugin"
    },
    "dynamicBindingPathList": [
      {
        "key": "body"
      }
    ],
    "executeOnLoad": false,
    "fullyQualifiedName": "JSObject1.Table1primaryColumnscustomColumn7onClick",
    "name": "Table1primaryColumnscustomColumn7onClick",
    "pageId": "Client",
    "userSetOnLoad": false
  }
}